setup.cfg
setup.py
RF433/__init__.py
RF433/test.py
RF433.egg-info/PKG-INFO
RF433.egg-info/SOURCES.txt
RF433.egg-info/dependency_links.txt
RF433.egg-info/requires.txt
RF433.egg-info/top_level.txt
RF433/driver/__init__.py
RF433/driver/arduino.py
RF433/protocols/__init__.py
RF433/protocols/home_easy.py
RF433/protocols/protocol.py