Metadata-Version: 1.1
Name: RF433
Version: 0.1.5
Summary: RF433 library to send signals for various protocols using                     an arduino
Home-page: https://github.com/bsilvr/pyRF433
Author: Bruno Silva
Author-email: brunomiguelsilva@ua.pt
License: LICENSE
Download-URL: https://github.com/bsilvr/pyRF433/tarball/0.1.5
Keywords: rf433,arduino
Platform: UNKNOWN
